prom433/__init__.py
prom433/arguments.py
prom433/exceptions.py
prom433/prometheus.py
prom433/server.py
prom433-2.6.2.data/scripts/prom433
tests/__init__.py
tests/test_arguments.py
tests/test_prometheus.py
tests/test_server.py
prom433-2.6.2.dist-info/LICENSE
prom433-2.6.2.dist-info/METADATA
prom433-2.6.2.dist-info/WHEEL
prom433-2.6.2.dist-info/top_level.txt
prom433-2.6.2.dist-info/RECORD
